InstanceReduction/DataPreparation.py
InstanceReduction/Raport.py
InstanceReduction/__init__.py
InstanceReduction/Reduction/DROP1.py
InstanceReduction/Reduction/ENN.py
InstanceReduction/Reduction/ICF.py
InstanceReduction/Reduction/MSS.py
InstanceReduction/Reduction/PSC.py
InstanceReduction/Reduction/_NNGraph.py
InstanceReduction/Reduction/_Reduction.py
InstanceReduction/Reduction/__init__.py
tests/DROP1_test.py
tests/DataPreparation_load_test.py
tests/DataPreparation_prepar_test.py
tests/ENN_test.py
tests/ICF_test.py
tests/MSS_test.py
tests/NNGraph_test.py
tests/PCS_test.py
tests/Raport_test.py
tests/__init__.py
tests/const.py
tests/test_reduction.py
data_reduction-0.0.1.dist-info/LICENSE
data_reduction-0.0.1.dist-info/METADATA
data_reduction-0.0.1.dist-info/WHEEL
data_reduction-0.0.1.dist-info/top_level.txt
data_reduction-0.0.1.dist-info/RECORD
